[
	{
		"time": 1607910786144,
		"file": "2020-12-14-01-53-06.zip",
		"index": 1,
		"success": true,
		"size": 30533651
	},
	{
		"time": 1607971684759,
		"file": "2020-12-14-18-48-04.zip",
		"index": 2,
		"success": true,
		"size": 32300702
	},
	{
		"time": 1607978884807,
		"file": "2020-12-14-20-48-04.zip",
		"index": 3,
		"success": true,
		"size": 33738949
	},
	{
		"time": 1607986084855,
		"file": "2020-12-14-22-48-04.zip",
		"index": 4,
		"success": true,
		"size": 33967746
	},
	{
		"time": 1607993284867,
		"file": "2020-12-15-00-48-04.zip",
		"index": 5,
		"success": true,
		"size": 43679344
	}
]